Metadata-Version: 2.1
Name: ansistrip
Version: 0.1
Summary: ASCII Screen Splash for SHYCD software.
Home-page: https://github.com/carlosplanchon/ansistrip
Author: Carlos A. Planchón
Author-email: bubbledoloresuruguay2@gmail.com
License: GPL3
Download-URL: https://github.com/carlosplanchon/ansistrip/archive/v0.1.tar.gz
Keywords: ascii,ansi,strip,VT100
Platform: UNKNOWN
Classifier: Intended Audience :: Developers
Classifier: Topic :: Software Development :: Build Tools
Classifier: License :: OSI Approved :: GNU General Public License v3 (GPLv3)
Classifier: Programming Language :: Python :: 3
Classifier: Programming Language :: Python :: 3.4
Classifier: Programming Language :: Python :: 3.5
Classifier: Programming Language :: Python :: 3.6
Classifier: Programming Language :: Python :: 3.7
